[
    {
        "fio": "Иванов Александр Петрович",
        "policy_number": "12345",
        "phone": "+375333642145",
        "object_insured": "Дом",
        "risk": "Пожар",
        "start_date": "09.10.2024",
        "end_date": "09.10.2026",
        "premium": 500.0,
        "coverage": 400.0,
        "agent": "Иванов И.И.",
        "timestamp": "2025-10-09 18:32:31",
        "previous_hash": "2237e233e0f1d7b1d1957c6c7f7515663bb8443d3c78667b4696522c57859f55",
        "current_hash": "3d6cd9e5ef2bcf50a793bbe8e7dee04f7cf57f6b6c3082356d059a5c6a5d5716"
    },
    {
        "fio": "Смирнова Анна Александровна",
        "policy_number": "123456",
        "phone": "+375336987456",
        "object_insured": "Автомобиль",
        "risk": "Угон",
        "start_date": "05.05.2025",
        "end_date": "05.05.2026",
        "premium": 300.0,
        "coverage": 200.0,
        "agent": "Петров П.П.",
        "timestamp": "2025-10-09 18:33:42",
        "previous_hash": "3d6cd9e5ef2bcf50a793bbe8e7dee04f7cf57f6b6c3082356d059a5c6a5d5716",
        "current_hash": "c60de7a90319fb5a482242d49ad7291871d7c059ee8449417156b72eba837933"
    },
    {
        "fio": "Петров Андрей Сергеевич",
        "policy_number": "1254",
        "phone": "+375336542598",
        "object_insured": "Мотоцикл",
        "risk": "ДТП",
        "start_date": "12.01.2025",
        "end_date": "12.03.2027",
        "premium": 200.0,
        "coverage": 100.0,
        "agent": "Сидорова А.А.",
        "timestamp": "2025-10-09 18:40:54",
        "previous_hash": "c60de7a90319fb5a482242d49ad7291871d7c059ee8449417156b72eba837933",
        "current_hash": "82e036019faea04eefed355868520ea8d4cbfd2fe6df18c0d990115f7716c7e2"
    },
    {
        "fio": "Иванов Александр Петрович",
        "policy_number": "14568",
        "phone": "+375298744563",
        "object_insured": "Смартфон",
        "risk": "Хищение",
        "start_date": "17.03.2024",
        "end_date": "17.03.2026",
        "premium": 100.0,
        "coverage": 100.0,
        "agent": "Кузнецов М.В.",
        "timestamp": "2025-10-09 18:42:01",
        "previous_hash": "82e036019faea04eefed355868520ea8d4cbfd2fe6df18c0d990115f7716c7e2",
        "current_hash": "c6daf02d9dfe3ff083b0f8b168409e72da8aea8290948be18a19ec10a2595513"
    },
    {
        "fio": "Алексеева Марта Ивановна",
        "policy_number": "1478",
        "phone": "+375336548952",
        "object_insured": "Багаж",
        "risk": "Утеря",
        "start_date": "14.07.2025",
        "end_date": "15.07.2026",
        "premium": 50.0,
        "coverage": 25.0,
        "agent": "Иванов И.И.",
        "timestamp": "2025-10-09 18:45:56",
        "previous_hash": "c6daf02d9dfe3ff083b0f8b168409e72da8aea8290948be18a19ec10a2595513",
        "current_hash": "e7798e7afa723f4859dd56180e0027a7964cbb6faf2c13eee8ea916c6f853cd5"
    },
    {
        "fio": "Сидоров Михаил Степанович",
        "policy_number": "12569",
        "phone": "+375298744123",
        "object_insured": "Авиабилеты",
        "risk": "Отмена поездки",
        "start_date": "18.10.2025",
        "end_date": "18.11.2025",
        "premium": 50.0,
        "coverage": 50.0,
        "agent": "Петров П.П.",
        "timestamp": "2025-10-09 18:47:27",
        "previous_hash": "e7798e7afa723f4859dd56180e0027a7964cbb6faf2c13eee8ea916c6f853cd5",
        "current_hash": "033e41e2527f2205968f69657467ea798a046a51291842c05abeb2773041b26a"
    },
    {
        "fio": "Михайлова Алеся Сергеевна",
        "policy_number": "5896",
        "phone": "+375336985263",
        "object_insured": "Круиз",
        "risk": "Отмена поездки",
        "start_date": "25.09.2025",
        "end_date": "20.10.2025",
        "premium": 30.0,
        "coverage": 30.0,
        "agent": "Сидорова А.А.",
        "timestamp": "2025-10-09 18:54:42",
        "previous_hash": "033e41e2527f2205968f69657467ea798a046a51291842c05abeb2773041b26a",
        "current_hash": "4e90dbc44ad587b0510bbfa7e06400f9e85040084e24d26dc918ab82111060e4"
    },
    {
        "fio": "Петрова Ирина Степановна",
        "policy_number": "15258",
        "phone": "+375336987412",
        "object_insured": "Телевизор",
        "risk": "Поломка",
        "start_date": "10.11.2025",
        "end_date": "10.12.2026",
        "premium": 300.0,
        "coverage": 400.0,
        "agent": "Кузнецов М.В.",
        "timestamp": "2025-11-28 17:58:45",
        "previous_hash": "4e90dbc44ad587b0510bbfa7e06400f9e85040084e24d26dc918ab82111060e4",
        "current_hash": "9ae4f1aca2362f0375cbc494b39b3325567f5e497942630c098ca8bcf1802709"
    }
]